authsign/__init__.py
authsign/acme_signer.py
authsign/crypto.py
authsign/log.py
authsign/main.py
authsign/model.py
authsign/signer.py
authsign/utils.py
authsign/verifier.py
authsign/trusted/__init__.py
authsign/trusted/roots.yaml
authsign/trusted/ts-chain.pem
authsign-0.5.2.data/data/log.json
authsign-0.5.2.data/data/requirements.txt
authsign-0.5.2.dist-info/METADATA
authsign-0.5.2.dist-info/WHEEL
authsign-0.5.2.dist-info/entry_points.txt
authsign-0.5.2.dist-info/top_level.txt
authsign-0.5.2.dist-info/zip-safe
authsign-0.5.2.dist-info/RECORD
