Metadata-Version: 2.1
Name: authsign
Version: 0.5.2
Summary: Authenticating Data Signing + Verification Server
Home-page: https://github.com/webrecorder/authsign
Author: Webrecorder Software
Author-email: info@webrecorder.net
License: UNKNOWN
Platform: UNKNOWN
Classifier: Development Status :: 4 - Beta
Classifier: Intended Audience :: Developers
Classifier: Programming Language :: Python
Classifier: Programming Language :: Python :: 3.7
Classifier: Programming Language :: Python :: 3.8
Classifier: License :: OSI Approved :: GNU General Public License v3 or later (GPLv3+)
Requires-Python: >=3.7
Requires-Dist: cryptography
Requires-Dist: rfc3161ng
Requires-Dist: pem
Requires-Dist: fastapi ==0.110.1
Requires-Dist: uvicorn
Requires-Dist: pyyaml
Requires-Dist: acme
Requires-Dist: pyasn1
Requires-Dist: python-dateutil
Requires-Dist: pydantic ==1.10.13
Requires-Dist: httpx <1.0,>=0.22.0
Requires-Dist: h11 <0.15,>=0.13
